ephios/__init__.py
ephios/__main__.py
ephios/api/__init__.py
ephios/api/access/auth.py
ephios/api/access/oauth2_urls.py
ephios/api/access/views.py
ephios/api/apps.py
ephios/api/fields.py
ephios/api/filters.py
ephios/api/migrations/0001_initial.py
ephios/api/migrations/0002_accesstoken_description_accesstoken_revoked_and_more.py
ephios/api/migrations/0003_application_post_logout_redirect_uris.py
ephios/api/migrations/0004_application_allowed_origins_and_more.py
ephios/api/migrations/0005_accesstoken_token_checksum_refreshtoken_token_family_and_more.py
ephios/api/migrations/__init__.py
ephios/api/models.py
ephios/api/permissions.py
ephios/api/serializers.py
ephios/api/signals.py
ephios/api/templates/api/access_token_form.html
ephios/api/templates/api/access_token_list.html
ephios/api/templates/api/access_token_reveal.html
ephios/api/templates/oauth2_provider/application_confirm_delete.html
ephios/api/templates/oauth2_provider/application_detail.html
ephios/api/templates/oauth2_provider/application_form.html
ephios/api/templates/oauth2_provider/application_list.html
ephios/api/templates/oauth2_provider/application_registration_form.html
ephios/api/templates/oauth2_provider/authorize.html
ephios/api/urls.py
ephios/api/views/events.py
ephios/api/views/users.py
ephios/asgi.py
ephios/core/__init__.py
ephios/core/admin.py
ephios/core/apps.py
ephios/core/calendar.py
ephios/core/checks.py
ephios/core/consequences.py
ephios/core/context.py
ephios/core/dynamic.py
ephios/core/dynamic_preferences_registry.py
ephios/core/forms/__init__.py
ephios/core/forms/auth.py
ephios/core/forms/events.py
ephios/core/forms/users.py
ephios/core/ical.py
ephios/core/management/__init__.py
ephios/core/management/commands/__init__.py
ephios/core/management/commands/build.py
ephios/core/management/commands/convert_mariadb_uuids.py
ephios/core/management/commands/devdata.py
ephios/core/management/commands/generate_vapid_key.py
ephios/core/management/commands/run_periodic.py
ephios-0.24.4.dist-info/LICENSE
ephios-0.24.4.dist-info/METADATA
ephios-0.24.4.dist-info/WHEEL
ephios-0.24.4.dist-info/RECORD
