Metadata-Version: 2.1
Name: ephios
Version: 0.24.4
Summary: ephios is a tool to manage shifts for medical services.
Home-page: https://ephios.de
License: MIT
Author: Julian Baumann
Author-email: julian@ephios.de
Requires-Python: >=3.10,<4.0
Classifier: License :: OSI Approved :: MIT License
Classifier: Programming Language :: Python :: 3
Classifier: Programming Language :: Python :: 3.10
Classifier: Programming Language :: Python :: 3.11
Classifier: Programming Language :: Python :: 3.12
Classifier: Programming Language :: Python :: 3.13
Provides-Extra: mysql
Provides-Extra: pgsql
Provides-Extra: redis
Requires-Dist: Django[argon2] (>=5.2,<5.3)
Requires-Dist: Markdown (>=3.3.7,<4.0.0)
Requires-Dist: beautifulsoup4 (>=4.13.3,<5.0.0)
Requires-Dist: black (>=24.10,<26.0)
Requires-Dist: bleach (>=6.0.0,<7.0.0)
Requires-Dist: crispy-bootstrap5 (>=0.7,<2025.7)
Requires-Dist: css-inline (>=0.10.3,<0.18.0)
Requires-Dist: django-compressor (>=4.5,<5.0)
Requires-Dist: django-coverage-plugin (>=2.0.3,<4.0.0)
Requires-Dist: django-crispy-forms (>=2.0,<3.0)
Requires-Dist: django-csp (>=4.0,<5.0)
Requires-Dist: django-dynamic-preferences (>=1.15.0,<2.0.0)
Requires-Dist: django-environ (>=0.11.2,<0.13)
Requires-Dist: django-filter (>=24,<26)
Requires-Dist: django-formset-js-improved (>=0.5.0,<0.6.0)
Requires-Dist: django-guardian (>=3.0.0,<4.0.0)
Requires-Dist: django-ical (>=1.8.3,<2.0.0)
Requires-Dist: django-libsass (>=0.9,<0.10)
Requires-Dist: django-oauth-toolkit (>=3.0.1,<3.1.0)
Requires-Dist: django-polymorphic (>=4.1,<5.0)
Requires-Dist: django-select2 (>=8.0,<9.0)
Requires-Dist: django-statici18n (>=2.3.1,<3.0.0)
Requires-Dist: django-webpush (>=0.3.5,<0.4.0)
Requires-Dist: djangorestframework (>=3.13.1,<4.0.0)
Requires-Dist: djangorestframework-guardian (>=0.3,<0.5)
Requires-Dist: drf-spectacular[sidecar] (>=0.27.2,<0.29.0)
Requires-Dist: lxml (>=4.9.3,<7.0.0)
Requires-Dist: mysqlclient (>=2.1.1,<3.0.0) ; extra == "mysql"
Requires-Dist: psycopg2 (>=2.9.3,<3.0.0) ; extra == "pgsql"
Requires-Dist: pyjwt (>=2.8.0,<3.0.0)
Requires-Dist: python-dateutil (>=2.9.0.post0,<3.0.0)
Requires-Dist: pyyaml (>=6.0.1,<7.0.0)
Requires-Dist: redis[hiredis] (>=5,<7) ; extra == "redis"
Requires-Dist: reportlab (>=3.6.11,<5.0.0)
Requires-Dist: requests (>=2.31.0,<3.0.0)
Requires-Dist: requests-oauthlib (>=2.0,<3.0)
Requires-Dist: scipy (>=1.12.0,<2.0.0)
Requires-Dist: uritemplate (>=4.1.1,<5.0.0)
Requires-Dist: urllib3 (>=2.5.0,<3.0.0)
Project-URL: Changelog, https://docs.ephios.de/en/latest/changelog.html
Project-URL: Coverage, https://coveralls.io/github/ephios-dev/ephios
Project-URL: Documentation, https://docs.ephios.de/en/stable/
Project-URL: Repository, https://github.com/ephios-dev/ephios
Project-URL: Report bugs, https://github.com/ephios-dev/ephios/issues
